setup.py
probability_distributions_888/Binomialdistribution.py
probability_distributions_888/Gaussiandistribution.py
probability_distributions_888/Generaldistribution.py
probability_distributions_888/__init__.py
probability_distributions_888.egg-info/PKG-INFO
probability_distributions_888.egg-info/SOURCES.txt
probability_distributions_888.egg-info/dependency_links.txt
probability_distributions_888.egg-info/not-zip-safe
probability_distributions_888.egg-info/top_level.txt