Metadata-Version: 1.0
Name: probability-distributions-888
Version: 0.2
Summary: Gaussian and Binomial distributions
Home-page: UNKNOWN
Author: Michael Mundell
Author-email: gbsnguy@gmail.com
License: UNKNOWN
Platform: UNKNOWN
